decs/__init__.py
decs/testing.py
decs/verification.py
tests/__init__.py
tests/test_testing.py
tests/test_verification.py
decs-0.0.4.dist-info/LICENSE
decs-0.0.4.dist-info/METADATA
decs-0.0.4.dist-info/WHEEL
decs-0.0.4.dist-info/top_level.txt
decs-0.0.4.dist-info/RECORD
