Metadata-Version: 2.1
Name: decs
Version: 0.0.4
Summary: A handful of useful general-purpose python decorators.
Home-page: https://github.com/python-packages/decs
Author: Sergey Kastryulin
Author-email: snk4tr@gmail.com
License: UNKNOWN
Platform: UNKNOWN
Classifier: Programming Language :: Python :: 3
Classifier: License :: OSI Approved :: MIT License
Classifier: Operating System :: OS Independent
Requires-Dist: numpy (==1.16.1)
